{".class": "MypyFile", "_fullname": "casting", "is_partial_stub_package": false, "is_stub": false, "names": {".class": "SymbolTable", "__doc__": {".class": "SymbolTableNode", "kind": "Gdef", "node": {".class": "Var", "flags": ["is_ready"], "fullname": "casting.__doc__", "name": "__doc__", "type": "builtins.str"}}, "__file__": {".class": "SymbolTableNode", "kind": "Gdef", "node": {".class": "Var", "flags": ["is_ready"], "fullname": "casting.__file__", "name": "__file__", "type": "builtins.str"}}, "__name__": {".class": "SymbolTableNode", "kind": "Gdef", "node": {".class": "Var", "flags": ["is_ready"], "fullname": "casting.__name__", "name": "__name__", "type": "builtins.str"}}, "__package__": {".class": "SymbolTableNode", "kind": "Gdef", "node": {".class": "Var", "flags": ["is_ready"], "fullname": "casting.__package__", "name": "__package__", "type": "builtins.str"}}, "vek": {".class": "SymbolTableNode", "kind": "Gdef", "node": {".class": "Var", "flags": [], "fullname": "casting.vek", "name": "vek", "type": "builtins.int"}}, "vstup": {".class": "SymbolTableNode", "kind": "Gdef", "node": {".class": "Var", "flags": [], "fullname": "casting.vstup", "name": "vstup", "type": "builtins.str"}}, "vstup2": {".class": "SymbolTableNode", "kind": "Gdef", "node": {".class": "Var", "flags": [], "fullname": "casting.vstup2", "name": "vstup2", "type": "builtins.int"}}}, "path": "casting.py"}